auto_schema/__init__.py
auto_schema/change.py
auto_schema/change_type.py
auto_schema/clause_text.py
auto_schema/clearable_string_io.py
auto_schema/command.py
auto_schema/compare.py
auto_schema/config.py
auto_schema/csv.py
auto_schema/diff.py
auto_schema/env.py
auto_schema/ops.py
auto_schema/ops_impl.py
auto_schema/renderers.py
auto_schema/runner.py
auto_schema/schema_item.py
auto_schema/script.py.mako
auto_schema/cli/__init__.py
auto_schema/util/__init__.py
auto_schema/util/os.py
auto_schema-0.0.34.dist-info/licenses/LICENSE
auto_schema-0.0.34.dist-info/METADATA
auto_schema-0.0.34.dist-info/WHEEL
auto_schema-0.0.34.dist-info/entry_points.txt
auto_schema-0.0.34.dist-info/top_level.txt
auto_schema-0.0.34.dist-info/RECORD
