Metadata-Version: 2.4
Name: auto_schema
Version: 0.0.34
Summary: auto schema for a db
Author-email: Ola Okelola <email@email.com>
Project-URL: Homepage, https://github.com/lolopinto/ent/tree/main/python/auto_schema
Project-URL: Bug Tracker, https://github.com/lolopinto/ent/tree/main/python/auto_schema/issues
Classifier: Programming Language :: Python :: 3
Classifier: License :: OSI Approved :: MIT License
Classifier: Operating System :: OS Independent
Requires-Python: >=3.11
License-File: LICENSE
Requires-Dist: sqlalchemy==2.0.18
Requires-Dist: lolopinto-alembic-fork==0.0.1.dev0
Requires-Dist: datetime==4.3
Requires-Dist: psycopg2==2.9.6
Requires-Dist: ruff==0.0.285
Requires-Dist: python-dateutil==2.8.2
Dynamic: license-file
